stbt/__init__.py
stbt/helpers.py
stbt/simulator.py
stbt/alphas/__init__.py
stbt/alphas/events.py
stbt/alphas/technical.py
stbt/download_ohlc/__init__.py
stbt/download_ohlc/cryptocurrency.py
stbt/operators/__init__.py
stbt/operators/technical.py
stbt-1.0.0.dist-info/AUTHORS.rst
stbt-1.0.0.dist-info/LICENSE.txt
stbt-1.0.0.dist-info/METADATA
stbt-1.0.0.dist-info/WHEEL
stbt-1.0.0.dist-info/top_level.txt
stbt-1.0.0.dist-info/RECORD
