Metadata-Version: 2.1
Name: stbt
Version: 1.0.0
Summary: Simple trading backtester
Home-page: https://github.com/bluella/stbt
Author: Igor Grigorev
Author-email: barsic1080@gmail.com
License: MIT
Platform: any
Classifier: Programming Language :: Python :: 3
Classifier: Operating System :: OS Independent
Classifier: License :: OSI Approved :: MIT License
Requires-Python: >=3.7
Requires-Dist: numpy
Requires-Dist: pandas
Requires-Dist: matplotlib
Requires-Dist: seaborn
Provides-Extra: testing
Requires-Dist: pytest ; extra == 'testing'
